README.md
pyproject.toml
setup.cfg
setup.py
openmapi/__init__.py
openmapi/fechas.py
openmapi/globales.py
openmapi/provincia.py
openmapi/registros.py
openmapi.egg-info/PKG-INFO
openmapi.egg-info/SOURCES.txt
openmapi.egg-info/dependency_links.txt
openmapi.egg-info/requires.txt
openmapi.egg-info/top_level.txt