Metadata-Version: 1.2
Name: openmapi
Version: 1.4.0
Summary: API COVID 19 por Provincias Argentinas
Home-page: https://github.com/Creativity-Hub/Open-mAPI
Author: Creativity Hub
Author-email: info.creativityhub@gmail.com
License: MIT
Download-URL: https://github.com/Creativity-Hub/Open-mAPI/archive/1.4.0.tar.gz
Project-URL: Bug Reports, https://github.com/IgnacioPardo/Open-mAPI/issues
Project-URL: Say Thanks!, https://saythanks.io/to/ignacio.pardo%40ort.edu.ar
Project-URL: Source, https://github.com/IgnacioPardo/Open-mAPI
Keywords: mAPI,Open_mAPI,covid19,Argentina
Platform: UNKNOWN
Classifier: Development Status :: 5 - Production/Stable
Classifier: Intended Audience :: Developers
Classifier: Topic :: Software Development :: Build Tools
Classifier: Topic :: Education
Classifier: Topic :: Scientific/Engineering :: Medical Science Apps.
Classifier: Topic :: Software Development :: Libraries
Classifier: License :: OSI Approved :: MIT License
Classifier: Programming Language :: Python :: 3
Classifier: Programming Language :: Python :: 3.5
Classifier: Programming Language :: Python :: 3.6
Classifier: Programming Language :: Python :: 3.7
Classifier: Programming Language :: Python :: 3.8
Classifier: Programming Language :: Python :: 3 :: Only
Requires-Python: >=3.5, <4
